odoo/addons/purchase_deposit_operating_unit/README.rst
odoo/addons/purchase_deposit_operating_unit/__init__.py
odoo/addons/purchase_deposit_operating_unit/__manifest__.py
odoo/addons/purchase_deposit_operating_unit/i18n/purchase_deposit_operating_unit.pot
odoo/addons/purchase_deposit_operating_unit/readme/CONTRIBUTORS.rst
odoo/addons/purchase_deposit_operating_unit/readme/DESCRIPTION.rst
odoo/addons/purchase_deposit_operating_unit/readme/USAGE.rst
odoo/addons/purchase_deposit_operating_unit/static/description/icon.png
odoo/addons/purchase_deposit_operating_unit/static/description/index.html
odoo/addons/purchase_deposit_operating_unit/tests/__init__.py
odoo/addons/purchase_deposit_operating_unit/tests/test_purchase_deposit_operating_unit.py
odoo/addons/purchase_deposit_operating_unit/wizard/__init__.py
odoo/addons/purchase_deposit_operating_unit/wizard/purchase_make_invoice_advance.py
odoo_addon_purchase_deposit_operating_unit-15.0.1.0.0.1.dist-info/METADATA
odoo_addon_purchase_deposit_operating_unit-15.0.1.0.0.1.dist-info/WHEEL
odoo_addon_purchase_deposit_operating_unit-15.0.1.0.0.1.dist-info/top_level.txt
odoo_addon_purchase_deposit_operating_unit-15.0.1.0.0.1.dist-info/RECORD
