Metadata-Version: 2.1
Name: odoo-addon-purchase_deposit_operating_unit
Version: 15.0.1.0.0.1
Summary: Adds the concecpt of operating unit (OU) when create purchase deposit
Home-page: https://github.com/OCA/operating-unit
Author: Ecosoft,Odoo Community Association (OCA)
Author-email: support@odoo-community.org
License: AGPL-3
Classifier: Programming Language :: Python
Classifier: Framework :: Odoo
Classifier: Framework :: Odoo :: 15.0
Classifier: License :: OSI Approved :: GNU Affero General Public License v3
Requires-Python: >=3.8
Requires-Dist: odoo-addon-purchase-deposit<15.1dev,>=15.0dev
Requires-Dist: odoo-addon-purchase-operating-unit<15.1dev,>=15.0dev
Requires-Dist: odoo<15.1dev,>=15.0a
